[
  {
    "id": 1,
    "type": "Agility",
    "startDate": "12/01/2023",
    "endDate": "12/01/2023",
    "lieu": "Darois",
    "illustration": "./agility.jpg",
    "Lien": ""
  },
  {
    "id": 2,
    "type": "Chien de berger",
    "startDate": "24/01/2023",
    "endDate": "24/01/2023",
    "lieu": "Beaune",
    "illustration": "./chien_berger.jpeg",
    "Lien": ""
  },
  {
    "id": 3,
    "type": "Soldes",
    "startDate": "12/02/2023",
    "endDate": "17/02/2023",
    "lieu": "",
    "illustration": "./soldes.jpg",
    "Lien": ""
  }
]